license
readme.rst
setup.py
w3g.py
w3g.egg-info/PKG-INFO
w3g.egg-info/SOURCES.txt
w3g.egg-info/dependency_links.txt
w3g.egg-info/entry_points.txt
w3g.egg-info/top_level.txt