Metadata-Version: 1.0
Name: w3g
Version: 1.0.3
Summary: Access Warcraft 3 replay files from Python 2 or 3.
Home-page: UNKNOWN
Author: Anthony Scopatz
Author-email: scopatz@gmail.com
License: CC0
Platform: UNKNOWN
